{
    "seed": 213,
    "ports": 4,
    "scenarios": 4,
    "obj": 34826.94684278411,
    "time": 1.5854778289794922,
    "gap": 0.0,
    "mean_load_per_port": [
        12288.09945678711,
        8794.651023424178,
        4231.922180983956
    ],
    "mean_teu_load_per_port": [
        16087.287109375,
        47430.29448410475,
        89985.52070534922
    ],
    "mean_load_per_location": [
        [
            [
                [
                    0.0,
                    333.0,
                    0.0,
                    0.0
                ],
                [
                    0.0,
                    250.0,
                    0.0,
                    0.0
                ]
            ],
            [
                [
                    0.0,
                    0.0,
                    0.0,
                    334.0
                ],
                [
                    0.0,
                    0.0,
                    0.0,
                    5.957611083984375
                ]
            ],
            [
                [
                    0.0,
                    0.0,
                    0.0,
                    334.0
                ],
                [
                    0.0,
                    83.0,
                    0.0,
                    334.0
                ]
            ],
            [
                [
                    0.0,
                    166.0,
                    289.8914443481601,
                    0.0
                ],
                [
                    0.0,
                    0.0,
                    167.0,
                    0.0
                ]
            ],
            [
                [
                    0.0,
                    167.0,
                    0.0,
                    0.0
                ],
                [
                    0.0,
                    266.09607696533203,
                    0.0,
                    0.0
                ]
            ],
            [
                [
                    0.0,
                    0.0,
                    0.0,
                    167.0
                ],
                [
                    0.0,
                    92.91705322265625,
                    0.0,
                    334.0
                ]
            ],
            [
                [
                    0.0,
                    334.0,
                    0.0,
                    166.0
                ],
                [
                    0.0,
                    28.495464324951172,
                    0.0,
                    83.0
                ]
            ],
            [
                [
                    0.0,
                    84.7852783203125,
                    0.0,
                    0.0
                ],
                [
                    0.0,
                    166.0,
                    0.0,
                    0.0
                ]
            ],
            [
                [
                    0.0,
                    412.7125549316406,
                    0.0,
                    0.0
                ],
                [
                    0.0,
                    334.0,
                    0.0,
                    0.0
                ]
            ],
            [
                [
                    0.0,
                    0.0,
                    372.29987716674805,
                    0.0
                ],
                [
                    0.0,
                    0.0,
                    417.0,
                    0.0
                ]
            ],
            [
                [
                    0.0,
                    0.0,
                    83.0,
                    0.0
                ],
                [
                    0.0,
                    334.0,
                    166.0,
                    0.0
                ]
            ],
            [
                [
                    0.0,
                    0.0,
                    333.0,
                    0.0
                ],
                [
                    0.0,
                    0.0,
                    185.12368502504003,
                    0.0
                ]
            ],
            [
                [
                    0.0,
                    0.0,
                    333.0,
                    0.0
                ],
                [
                    0.0,
                    0.0,
                    500.0,
                    0.0
                ]
            ],
            [
                [
                    0.0,
                    0.0,
                    0.0,
                    417.0
                ],
                [
                    0.0,
                    0.0,
                    0.0,
                    286.0124320983887
                ]
            ],
            [
                [
                    0.0,
                    0.0,
                    0.0,
                    334.0
                ],
                [
                    0.0,
                    166.0,
                    0.0,
                    167.0
                ]
            ],
            [
                [
                    0.0,
                    0.0,
                    90.3709427856133,
                    252.39616012573242
                ],
                [
                    0.0,
                    0.0,
                    166.0,
                    167.0
                ]
            ],
            [
                [
                    0.0,
                    0.0,
                    333.0,
                    0.0
                ],
                [
                    0.0,
                    0.0,
                    500.0,
                    0.0
                ]
            ],
            [
                [
                    0.0,
                    0.0,
                    167.0,
                    0.0
                ],
                [
                    0.0,
                    0.0,
                    167.0,
                    83.0
                ]
            ],
            [
                [
                    0.0,
                    0.0,
                    83.0,
                    140.5720329284668
                ],
                [
                    0.0,
                    0.0,
                    83.0,
                    167.0
                ]
            ],
            [
                [
                    0.0,
                    267.15675354003906,
                    166.0,
                    0.0
                ],
                [
                    0.0,
                    334.0,
                    95.31208992004395,
                    0.0
                ]
            ]
        ],
        [
            [
                [
                    0.0,
                    0.0,
                    103.11882472038269,
                    63.3358089029789
                ],
                [
                    0.0,
                    0.0,
                    350.2961730957031,
                    90.05332612991333
                ]
            ],
            [
                [
                    0.0,
                    0.0,
                    125.0,
                    55.92382687330246
                ],
                [
                    0.0,
                    0.0,
                    98.89149856567383,
                    125.25
                ]
            ],
            [
                [
                    0.0,
                    0.0,
                    144.44524383544922,
                    88.9522655904293
                ],
                [
                    0.0,
                    0.0,
                    125.0,
                    138.51896104216576
                ]
            ],
            [
                [
                    0.0,
                    0.0,
                    104.25,
                    101.47041702270508
                ],
                [
                    0.0,
                    0.0,
                    31.417105436325073,
                    98.00180435180664
                ]
            ],
            [
                [
                    0.0,
                    0.0,
                    104.0,
                    62.5880012512207
                ],
                [
                    0.0,
                    0.0,
                    145.75,
                    62.5
                ]
            ],
            [
                [
                    0.0,
                    0.0,
                    184.37861628830433,
                    50.29655838012695
                ],
                [
                    0.0,
                    0.0,
                    23.375850677490234,
                    101.87414932250977
                ]
            ],
            [
                [
                    0.0,
                    0.0,
                    107.4265076071024,
                    95.20094299316406
                ],
                [
                    0.0,
                    0.0,
                    128.15712356567383,
                    74.93124413490295
                ]
            ],
            [
                [
                    0.0,
                    0.0,
                    24.3544921875,
                    178.88241773843765
                ],
                [
                    0.0,
                    0.0,
                    41.5,
                    131.4928960800171
                ]
            ],
            [
                [
                    0.0,
                    0.0,
                    41.75,
                    207.88427734375
                ],
                [
                    0.0,
                    0.0,
                    0.0,
                    224.7297114431858
                ]
            ],
            [
                [
                    0.0,
                    0.0,
                    128.9713010787964,
                    84.395751953125
                ],
                [
                    0.0,
                    0.0,
                    145.84540367126465,
                    0.0
                ]
            ],
            [
                [
                    0.0,
                    0.0,
                    142.67869567871094,
                    60.363019943237305
                ],
                [
                    0.0,
                    0.0,
                    63.59089756011963,
                    83.5
                ]
            ],
            [
                [
                    0.0,
                    0.0,
                    149.32822340726852,
                    69.32658424973488
                ],
                [
                    0.0,
                    0.0,
                    134.3419246673584,
                    166.5
                ]
            ],
            [
                [
                    0.0,
                    0.0,
                    96.05786323547363,
                    25.316879272460938
                ],
                [
                    0.0,
                    0.0,
                    191.81473964452744,
                    86.33673048019409
                ]
            ],
            [
                [
                    0.0,
                    0.0,
                    20.75,
                    189.82041129469872
                ],
                [
                    0.0,
                    0.0,
                    145.75,
                    155.13616180419922
                ]
            ],
            [
                [
                    0.0,
                    0.0,
                    129.89108657836914,
                    97.35271072387695
                ],
                [
                    0.0,
                    0.0,
                    94.30899274349213,
                    76.32345849275589
                ]
            ],
            [
                [
                    0.0,
                    0.0,
                    157.884584993124,
                    83.25
                ],
                [
                    0.0,
                    0.0,
                    186.88298416137695,
                    68.93609619140625
                ]
            ],
            [
                [
                    0.0,
                    0.0,
                    145.96729248066725,
                    140.2232894897461
                ],
                [
                    0.0,
                    0.0,
                    83.25,
                    146.0
                ]
            ],
            [
                [
                    0.0,
                    0.0,
                    143.51059114933014,
                    30.770634829998016
                ],
                [
                    0.0,
                    0.0,
                    111.10038397411523,
                    83.5
                ]
            ],
            [
                [
                    0.0,
                    0.0,
                    279.03508377075195,
                    62.25
                ],
                [
                    0.0,
                    0.0,
                    137.36429171264172,
                    55.556800028591724
                ]
            ],
            [
                [
                    0.0,
                    0.0,
                    209.79672926664352,
                    175.6229124069214
                ],
                [
                    0.0,
                    0.0,
                    121.05046790897914,
                    0.0
                ]
            ]
        ],
        [
            [
                [
                    0.0,
                    0.0,
                    0.0,
                    228.11449519358575
                ],
                [
                    0.0,
                    0.0,
                    0.0,
                    166.43812892332647
                ]
            ],
            [
                [
                    0.0,
                    0.0,
                    0.0,
                    54.47853874787688
                ],
                [
                    0.0,
                    0.0,
                    0.0,
                    104.36159793204777
                ]
            ],
            [
                [
                    0.0,
                    0.0,
                    0.0,
                    78.4926842879504
                ],
                [
                    0.0,
                    0.0,
                    0.0,
                    77.93627771735191
                ]
            ],
            [
                [
                    0.0,
                    0.0,
                    0.0,
                    88.00580352544785
                ],
                [
                    0.0,
                    0.0,
                    0.0,
                    106.40062179809547
                ]
            ],
            [
                [
                    0.0,
                    0.0,
                    0.0,
                    123.09857517294586
                ],
                [
                    0.0,
                    0.0,
                    0.0,
                    61.883843642840056
                ]
            ],
            [
                [
                    0.0,
                    0.0,
                    0.0,
                    78.79455459676683
                ],
                [
                    0.0,
                    0.0,
                    0.0,
                    26.342591881752014
                ]
            ],
            [
                [
                    0.0,
                    0.0,
                    0.0,
                    84.63002472370863
                ],
                [
                    0.0,
                    0.0,
                    0.0,
                    180.46640264242887
                ]
            ],
            [
                [
                    0.0,
                    0.0,
                    0.0,
                    51.51916611008346
                ],
                [
                    0.0,
                    0.0,
                    0.0,
                    125.28243574500084
                ]
            ],
            [
                [
                    0.0,
                    0.0,
                    0.0,
                    112.89890566885735
                ],
                [
                    0.0,
                    0.0,
                    0.0,
                    110.65949442982674
                ]
            ],
            [
                [
                    0.0,
                    0.0,
                    0.0,
                    119.35222951322794
                ],
                [
                    0.0,
                    0.0,
                    0.0,
                    108.45479840446606
                ]
            ],
            [
                [
                    0.0,
                    0.0,
                    0.0,
                    121.96480552852154
                ],
                [
                    0.0,
                    0.0,
                    0.0,
                    78.28824898600578
                ]
            ],
            [
                [
                    0.0,
                    0.0,
                    0.0,
                    118.70637856051326
                ],
                [
                    0.0,
                    0.0,
                    0.0,
                    88.72585140354931
                ]
            ],
            [
                [
                    0.0,
                    0.0,
                    0.0,
                    142.52440554462373
                ],
                [
                    0.0,
                    0.0,
                    0.0,
                    64.31919133663177
                ]
            ],
            [
                [
                    0.0,
                    0.0,
                    0.0,
                    106.42161297425628
                ],
                [
                    0.0,
                    0.0,
                    0.0,
                    157.02176063356913
                ]
            ],
            [
                [
                    0.0,
                    0.0,
                    0.0,
                    113.54281041957438
                ],
                [
                    0.0,
                    0.0,
                    0.0,
                    70.88691549144421
                ]
            ],
            [
                [
                    0.0,
                    0.0,
                    0.0,
                    86.48065052554011
                ],
                [
                    0.0,
                    0.0,
                    0.0,
                    102.83700108528137
                ]
            ],
            [
                [
                    0.0,
                    0.0,
                    0.0,
                    103.3406990468502
                ],
                [
                    0.0,
                    0.0,
                    0.0,
                    95.9577877151107
                ]
            ],
            [
                [
                    0.0,
                    0.0,
                    0.0,
                    92.60215663909912
                ],
                [
                    0.0,
                    0.0,
                    0.0,
                    154.72858110827218
                ]
            ],
            [
                [
                    0.0,
                    0.0,
                    0.0,
                    123.55936916172504
                ],
                [
                    0.0,
                    0.0,
                    0.0,
                    46.87237513845882
                ]
            ],
            [
                [
                    0.0,
                    0.0,
                    0.0,
                    204.79239239171147
                ],
                [
                    0.0,
                    0.0,
                    0.0,
                    70.73801663563111
                ]
            ]
        ]
    ],
    "mean_hatch_overstowage": [
        0.0,
        0.0,
        0.0
    ],
    "mean_ci": [
        1536.0124320983887,
        1032.3515864312649,
        458.72182569094
    ],
    "mean_demand": [
        12288.09945678711,
        8258.812691450119,
        3669.77460552752
    ],
    "mean_revenue": [
        21166.295330585126,
        11004.72896488007,
        3801.307904202907
    ],
    "mean_cost": [
        0.0,
        0.0,
        0.0
    ],
    "mean_pd": [
        40.0,
        40.0,
        40.0
    ],
    "mean_mixing": [
        0.0,
        0.0,
        0.0
    ]
}