{
    "seed": 420,
    "ports": 4,
    "scenarios": 16,
    "obj": 18736.951648069462,
    "time": 309.1975967884064,
    "gap": 0.0,
    "mean_load_per_port": [
        10444.705103874207,
        1248.5596316352198,
        69.36451681656978
    ],
    "mean_teu_load_per_port": [
        12622.534803390503,
        26846.47197338452,
        22539.110465463324
    ],
    "mean_load_per_location": [
        [
            [
                [
                    0.0,
                    293.177791595459,
                    166.0,
                    0.0
                ],
                [
                    0.0,
                    56.69855499267578,
                    83.0,
                    0.0
                ]
            ],
            [
                [
                    0.0,
                    0.0,
                    53.37983703613281,
                    236.33195436000824
                ],
                [
                    0.0,
                    0.0,
                    83.0,
                    334.0
                ]
            ],
            [
                [
                    0.0,
                    0.0,
                    0.0,
                    333.0
                ],
                [
                    0.0,
                    0.0,
                    0.0,
                    265.87634658813477
                ]
            ],
            [
                [
                    0.0,
                    52.3829345703125,
                    0.0,
                    166.0
                ],
                [
                    0.0,
                    334.0,
                    0.0,
                    83.0
                ]
            ],
            [
                [
                    0.0,
                    170.20520341396332,
                    0.0,
                    0.0
                ],
                [
                    0.0,
                    500.0,
                    0.0,
                    0.0
                ]
            ],
            [
                [
                    0.0,
                    100.83766615390778,
                    48.25633120536804,
                    0.0
                ],
                [
                    0.0,
                    334.0,
                    152.28893721103668,
                    0.0
                ]
            ],
            [
                [
                    0.0,
                    0.0,
                    0.0,
                    273.4345271587372
                ],
                [
                    0.0,
                    92.35186767578125,
                    0.0,
                    304.4188085794449
                ]
            ],
            [
                [
                    0.0,
                    0.0,
                    0.0,
                    166.0
                ],
                [
                    0.0,
                    334.0,
                    0.0,
                    135.3829345703125
                ]
            ],
            [
                [
                    0.0,
                    0.0,
                    0.0,
                    166.0
                ],
                [
                    0.0,
                    0.0,
                    334.0,
                    166.0
                ]
            ],
            [
                [
                    0.0,
                    0.0,
                    327.9635009765625,
                    0.0
                ],
                [
                    0.0,
                    0.0,
                    218.60927486419678,
                    0.0
                ]
            ],
            [
                [
                    0.0,
                    0.0,
                    0.0,
                    0.0
                ],
                [
                    0.0,
                    334.0,
                    0.0,
                    0.0
                ]
            ],
            [
                [
                    0.0,
                    336.47858810424805,
                    0.0,
                    0.0
                ],
                [
                    0.0,
                    0.0,
                    0.0,
                    0.0
                ]
            ],
            [
                [
                    0.0,
                    0.0,
                    166.0,
                    0.0
                ],
                [
                    0.0,
                    0.0,
                    130.96794891357422,
                    0.0
                ]
            ],
            [
                [
                    0.0,
                    0.0,
                    268.8714294433594,
                    166.0
                ],
                [
                    0.0,
                    0.0,
                    334.0,
                    166.0
                ]
            ],
            [
                [
                    0.0,
                    0.0,
                    0.0,
                    111.30238652229309
                ],
                [
                    0.0,
                    0.0,
                    83.0,
                    167.0
                ]
            ],
            [
                [
                    0.0,
                    0.0,
                    166.0,
                    0.0
                ],
                [
                    0.0,
                    0.0,
                    83.0,
                    0.0
                ]
            ],
            [
                [
                    0.0,
                    0.0,
                    166.0,
                    0.0
                ],
                [
                    0.0,
                    0.0,
                    38.46280348300934,
                    0.0
                ]
            ],
            [
                [
                    0.0,
                    166.0,
                    0.0,
                    0.0
                ],
                [
                    0.0,
                    198.02547645568848,
                    0.0,
                    0.0
                ]
            ],
            [
                [
                    0.0,
                    83.0,
                    0.0,
                    167.0
                ],
                [
                    0.0,
                    0.0,
                    0.0,
                    334.0
                ]
            ],
            [
                [
                    0.0,
                    250.0,
                    0.0,
                    0.0
                ],
                [
                    0.0,
                    166.0,
                    0.0,
                    0.0
                ]
            ]
        ],
        [
            [
                [
                    0.0,
                    0.0,
                    0.0,
                    39.14531534910202
                ],
                [
                    0.0,
                    0.0,
                    0.0,
                    0.0
                ]
            ],
            [
                [
                    0.0,
                    0.0,
                    10.4375,
                    0.0
                ],
                [
                    0.0,
                    0.0,
                    0.0,
                    0.0
                ]
            ],
            [
                [
                    0.0,
                    0.0,
                    0.0,
                    5.1875
                ],
                [
                    0.0,
                    0.0,
                    112.14122339338064,
                    0.0
                ]
            ],
            [
                [
                    0.0,
                    0.0,
                    78.8723680973053,
                    0.0
                ],
                [
                    0.0,
                    0.0,
                    0.0,
                    0.0
                ]
            ],
            [
                [
                    0.0,
                    0.0,
                    0.17451627651803636,
                    0.0
                ],
                [
                    0.0,
                    0.0,
                    0.0,
                    2.6332649015116045
                ]
            ],
            [
                [
                    0.0,
                    0.0,
                    0.0,
                    0.0
                ],
                [
                    0.0,
                    0.0,
                    18.859083499269563,
                    0.0
                ]
            ],
            [
                [
                    0.0,
                    0.0,
                    146.79082834720612,
                    0.0
                ],
                [
                    0.0,
                    0.0,
                    89.59101867675781,
                    2.1075354631651644
                ]
            ],
            [
                [
                    0.0,
                    0.0,
                    13.887056422978635,
                    0.0
                ],
                [
                    0.0,
                    0.0,
                    0.0,
                    0.0
                ]
            ],
            [
                [
                    0.0,
                    0.0,
                    0.0,
                    0.0
                ],
                [
                    0.0,
                    0.0,
                    0.0,
                    5.1875
                ]
            ],
            [
                [
                    0.0,
                    0.0,
                    0.0,
                    117.68627834320068
                ],
                [
                    0.0,
                    0.0,
                    20.875,
                    110.35009241104126
                ]
            ],
            [
                [
                    0.0,
                    0.0,
                    0.0,
                    35.29799270629883
                ],
                [
                    0.0,
                    0.0,
                    0.0,
                    0.0
                ]
            ],
            [
                [
                    0.0,
                    0.0,
                    90.80548858642578,
                    0.0
                ],
                [
                    0.0,
                    0.0,
                    5.1875,
                    0.0
                ]
            ],
            [
                [
                    0.0,
                    0.0,
                    57.22945523262024,
                    10.964126586914062
                ],
                [
                    0.0,
                    0.0,
                    7.16049635432887,
                    27.754717403740617
                ]
            ],
            [
                [
                    0.0,
                    0.0,
                    10.4375,
                    0.0
                ],
                [
                    0.0,
                    0.0,
                    60.268760324906964,
                    29.98469975771328
                ]
            ],
            [
                [
                    0.0,
                    0.0,
                    16.25992202758789,
                    0.0
                ],
                [
                    0.0,
                    0.0,
                    0.0,
                    0.0
                ]
            ],
            [
                [
                    0.0,
                    0.0,
                    8.420128226280212,
                    59.17087936401367
                ],
                [
                    0.0,
                    0.0,
                    0.0,
                    7.13199520111084
                ]
            ],
            [
                [
                    0.0,
                    0.0,
                    0.0,
                    0.0
                ],
                [
                    0.0,
                    0.0,
                    27.979320526123047,
                    0.0
                ]
            ],
            [
                [
                    0.0,
                    0.0,
                    0.0,
                    0.0
                ],
                [
                    0.0,
                    0.0,
                    0.0,
                    0.0
                ]
            ],
            [
                [
                    0.0,
                    0.0,
                    0.0,
                    0.0
                ],
                [
                    0.0,
                    0.0,
                    0.0,
                    0.0
                ]
            ],
            [
                [
                    0.0,
                    0.0,
                    1.2757219076156616,
                    0.0
                ],
                [
                    0.0,
                    0.0,
                    12.865847791171584,
                    6.438998456931484
                ]
            ]
        ],
        [
            [
                [
                    0.0,
                    0.0,
                    0.0,
                    0.686119607170872
                ],
                [
                    0.0,
                    0.0,
                    0.0,
                    0.9952228297127872
                ]
            ],
            [
                [
                    0.0,
                    0.0,
                    0.0,
                    3.2509527921689085
                ],
                [
                    0.0,
                    0.0,
                    0.0,
                    1.063081945830611
                ]
            ],
            [
                [
                    0.0,
                    0.0,
                    0.0,
                    0.025006376206874847
                ],
                [
                    0.0,
                    0.0,
                    0.0,
                    1.65055833816053
                ]
            ],
            [
                [
                    0.0,
                    0.0,
                    0.0,
                    0.0
                ],
                [
                    0.0,
                    0.0,
                    0.0,
                    1.3819686712368549
                ]
            ],
            [
                [
                    0.0,
                    0.0,
                    0.0,
                    0.726051926612854
                ],
                [
                    0.0,
                    0.0,
                    0.0,
                    1.384394074804561
                ]
            ],
            [
                [
                    0.0,
                    0.0,
                    0.0,
                    0.0
                ],
                [
                    0.0,
                    0.0,
                    0.0,
                    1.115225321287069
                ]
            ],
            [
                [
                    0.0,
                    0.0,
                    0.0,
                    13.94232177734375
                ],
                [
                    0.0,
                    0.0,
                    0.0,
                    1.4727984213420182
                ]
            ],
            [
                [
                    0.0,
                    0.0,
                    0.0,
                    0.0
                ],
                [
                    0.0,
                    0.0,
                    0.0,
                    2.65100015051022
                ]
            ],
            [
                [
                    0.0,
                    0.0,
                    0.0,
                    0.0
                ],
                [
                    0.0,
                    0.0,
                    0.0,
                    2.5903257237237756
                ]
            ],
            [
                [
                    0.0,
                    0.0,
                    0.0,
                    0.0
                ],
                [
                    0.0,
                    0.0,
                    0.0,
                    1.7453494888368728
                ]
            ],
            [
                [
                    0.0,
                    0.0,
                    0.0,
                    0.0
                ],
                [
                    0.0,
                    0.0,
                    0.0,
                    1.126498990541302
                ]
            ],
            [
                [
                    0.0,
                    0.0,
                    0.0,
                    13.304380416870117
                ],
                [
                    0.0,
                    0.0,
                    0.0,
                    1.9164425559009597
                ]
            ],
            [
                [
                    0.0,
                    0.0,
                    0.0,
                    5.060892403125763
                ],
                [
                    0.0,
                    0.0,
                    0.0,
                    1.354697146966262
                ]
            ],
            [
                [
                    0.0,
                    0.0,
                    0.0,
                    0.0
                ],
                [
                    0.0,
                    0.0,
                    0.0,
                    1.655198362597968
                ]
            ],
            [
                [
                    0.0,
                    0.0,
                    0.0,
                    0.0
                ],
                [
                    0.0,
                    0.0,
                    0.0,
                    1.5319302130215642
                ]
            ],
            [
                [
                    0.0,
                    0.0,
                    0.0,
                    0.0
                ],
                [
                    0.0,
                    0.0,
                    0.0,
                    1.6314040838868882
                ]
            ],
            [
                [
                    0.0,
                    0.0,
                    0.0,
                    0.013128588243206042
                ],
                [
                    0.0,
                    0.0,
                    0.0,
                    1.137556786474886
                ]
            ],
            [
                [
                    0.0,
                    0.0,
                    0.0,
                    2.9693711685850164
                ],
                [
                    0.0,
                    0.0,
                    0.0,
                    1.1211060995404432
                ]
            ],
            [
                [
                    0.0,
                    0.0,
                    0.0,
                    0.0938106940313666
                ],
                [
                    0.0,
                    0.0,
                    0.0,
                    0.8817285656630434
                ]
            ],
            [
                [
                    0.0,
                    0.0,
                    0.0,
                    0.008922340648234585
                ],
                [
                    0.0,
                    0.0,
                    0.0,
                    0.8770709555241396
                ]
            ]
        ]
    ],
    "mean_hatch_overstowage": [
        0.0,
        0.0,
        0.0
    ],
    "mean_ci": [
        1305.5881379842758,
        1069.1682988852262,
        477.27310184136877
    ],
    "mean_demand": [
        10444.705103874207,
        8553.34639108181,
        3818.18481473095
    ],
    "mean_revenue": [
        17693.354453447115,
        1492.5771422221478,
        62.76081994631464
    ],
    "mean_cost": [
        0.0,
        0.0,
        0.0
    ],
    "mean_pd": [
        40.0,
        40.0,
        40.0
    ],
    "mean_mixing": [
        0.0,
        0.0,
        0.0
    ]
}