{
    "seed": 342,
    "ports": 4,
    "scenarios": 24,
    "obj": 34176.449651078634,
    "time": 59.95011806488037,
    "gap": 0.0,
    "mean_load_per_port": [
        12224.248990535736,
        8882.945665530897,
        4390.972279919465
    ],
    "mean_teu_load_per_port": [
        16403.361377239227,
        285478.7636158169,
        3368252.9426934794
    ],
    "mean_load_per_location": [
        [
            [
                [
                    0.0,
                    0.0,
                    166.0,
                    0.0
                ],
                [
                    0.0,
                    334.0,
                    166.0,
                    0.0
                ]
            ],
            [
                [
                    0.0,
                    167.0,
                    0.0,
                    158.20735961198807
                ],
                [
                    0.0,
                    0.0,
                    0.0,
                    96.46469116210938
                ]
            ],
            [
                [
                    0.0,
                    0.0,
                    166.0,
                    0.0
                ],
                [
                    0.0,
                    167.0,
                    83.0,
                    0.0
                ]
            ],
            [
                [
                    0.0,
                    334.0,
                    0.0,
                    166.0
                ],
                [
                    0.0,
                    328.42047119140625,
                    0.0,
                    166.0
                ]
            ],
            [
                [
                    0.0,
                    9.1051025390625,
                    167.0,
                    0.0
                ],
                [
                    0.0,
                    83.0,
                    41.84054812788962,
                    0.0
                ]
            ],
            [
                [
                    0.0,
                    166.0,
                    212.0036163330078,
                    0.0
                ],
                [
                    0.0,
                    157.21424865722656,
                    334.0,
                    0.0
                ]
            ],
            [
                [
                    0.0,
                    0.0,
                    0.0,
                    500.0
                ],
                [
                    0.0,
                    0.0,
                    0.0,
                    158.81325882673264
                ]
            ],
            [
                [
                    0.0,
                    0.0,
                    0.0,
                    452.2178649902344
                ],
                [
                    0.0,
                    0.0,
                    0.0,
                    417.0
                ]
            ],
            [
                [
                    0.0,
                    254.26654052734375,
                    166.0,
                    0.0
                ],
                [
                    0.0,
                    155.54671829938886,
                    83.0,
                    0.0
                ]
            ],
            [
                [
                    0.0,
                    167.0,
                    0.0,
                    166.0
                ],
                [
                    0.0,
                    0.0,
                    0.0,
                    83.0
                ]
            ],
            [
                [
                    0.0,
                    166.0,
                    0.0,
                    0.0
                ],
                [
                    0.0,
                    250.0,
                    0.0,
                    0.0
                ]
            ],
            [
                [
                    0.0,
                    0.0,
                    167.0,
                    166.0
                ],
                [
                    0.0,
                    0.0,
                    167.0,
                    83.0
                ]
            ],
            [
                [
                    0.0,
                    30.9473876953125,
                    166.0,
                    0.0
                ],
                [
                    0.0,
                    334.0,
                    135.0491542816162,
                    0.0
                ]
            ],
            [
                [
                    0.0,
                    0.0,
                    281.3788555562496,
                    0.0
                ],
                [
                    0.0,
                    0.0,
                    495.6522682607174,
                    0.0
                ]
            ],
            [
                [
                    0.0,
                    83.0,
                    334.0,
                    0.0
                ],
                [
                    0.0,
                    0.0,
                    334.0,
                    0.0
                ]
            ],
            [
                [
                    0.0,
                    0.0,
                    0.0,
                    250.0
                ],
                [
                    0.0,
                    0.0,
                    0.0,
                    263.24239349365234
                ]
            ],
            [
                [
                    0.0,
                    166.0,
                    167.0,
                    0.0
                ],
                [
                    0.0,
                    166.0,
                    334.0,
                    0.0
                ]
            ],
            [
                [
                    0.0,
                    19.96686965227127,
                    85.84883856773376,
                    0.0
                ],
                [
                    0.0,
                    0.0,
                    83.00000000000001,
                    0.0
                ]
            ],
            [
                [
                    0.0,
                    83.0,
                    0.0,
                    167.0
                ],
                [
                    0.0,
                    83.0,
                    0.0,
                    239.83438873291016
                ]
            ],
            [
                [
                    0.0,
                    0.0,
                    114.27773886919022,
                    167.0
                ],
                [
                    0.0,
                    0.0,
                    115.9285880625248,
                    255.02208709716797
                ]
            ]
        ],
        [
            [
                [
                    0.0,
                    0.0,
                    163.56660620093888,
                    80.37938732560724
                ],
                [
                    0.0,
                    0.0,
                    127.62763448939138,
                    102.26357895976328
                ]
            ],
            [
                [
                    0.0,
                    0.0,
                    109.87131904613561,
                    116.51492177115547
                ],
                [
                    0.0,
                    0.0,
                    161.40035800859468,
                    122.89725184543869
                ]
            ],
            [
                [
                    0.0,
                    0.0,
                    138.78519921625653,
                    76.90860481808583
                ],
                [
                    0.0,
                    0.0,
                    126.19553114510659,
                    92.57816501506632
                ]
            ],
            [
                [
                    0.0,
                    0.0,
                    103.07964225734274,
                    131.83623164561723
                ],
                [
                    0.0,
                    0.0,
                    95.65919676423073,
                    91.29728880632625
                ]
            ],
            [
                [
                    0.0,
                    0.0,
                    142.11158287522878,
                    106.63787408669789
                ],
                [
                    0.0,
                    0.0,
                    117.76320388168097,
                    78.57429967448115
                ]
            ],
            [
                [
                    0.0,
                    0.0,
                    57.21538819372654,
                    127.01637951994257
                ],
                [
                    0.0,
                    0.0,
                    86.44635715174593,
                    82.4267545277046
                ]
            ],
            [
                [
                    0.0,
                    0.0,
                    166.11151193082333,
                    93.28510565062363
                ],
                [
                    0.0,
                    0.0,
                    137.85604234660664,
                    116.27214353065938
                ]
            ],
            [
                [
                    0.0,
                    0.0,
                    74.4659336283803,
                    67.77119649034272
                ],
                [
                    0.0,
                    0.0,
                    92.18935188526909,
                    66.95385856899445
                ]
            ],
            [
                [
                    0.0,
                    0.0,
                    212.15545242225775,
                    173.07504121462503
                ],
                [
                    0.0,
                    0.0,
                    156.41666666666666,
                    116.0641694412463
                ]
            ],
            [
                [
                    0.0,
                    0.0,
                    101.1974874912864,
                    109.68296110009153
                ],
                [
                    0.0,
                    0.0,
                    92.59289158806416,
                    71.44310806194942
                ]
            ],
            [
                [
                    0.0,
                    0.0,
                    115.0210684318509,
                    129.8437096851671
                ],
                [
                    0.0,
                    0.0,
                    160.05057471990585,
                    80.8281718968517
                ]
            ],
            [
                [
                    0.0,
                    0.0,
                    98.11445640524228,
                    133.4371569366712
                ],
                [
                    0.0,
                    0.0,
                    75.58748092129827,
                    134.09900833790502
                ]
            ],
            [
                [
                    0.0,
                    0.0,
                    60.455205467511746,
                    112.15887094877606
                ],
                [
                    0.0,
                    0.0,
                    113.85327804953546,
                    90.65991369862525
                ]
            ],
            [
                [
                    0.0,
                    0.0,
                    158.59832176969698,
                    124.24876942816707
                ],
                [
                    0.0,
                    0.0,
                    103.42626882991885,
                    80.80206738950476
                ]
            ],
            [
                [
                    0.0,
                    0.0,
                    115.37507823687046,
                    84.45242577406079
                ],
                [
                    0.0,
                    0.0,
                    139.02342184120656,
                    129.64805283024907
                ]
            ],
            [
                [
                    0.0,
                    0.0,
                    82.96819463123877,
                    145.23663821506003
                ],
                [
                    0.0,
                    0.0,
                    85.1031874306085,
                    167.97583877449725
                ]
            ],
            [
                [
                    0.0,
                    0.0,
                    70.90561873657862,
                    121.27419614543517
                ],
                [
                    0.0,
                    0.0,
                    81.14972490351647,
                    130.7224261673788
                ]
            ],
            [
                [
                    0.0,
                    0.0,
                    140.9165870733559,
                    69.47986161708832
                ],
                [
                    0.0,
                    0.0,
                    120.48783637334903,
                    87.28050104777019
                ]
            ],
            [
                [
                    0.0,
                    0.0,
                    110.50854174792767,
                    113.5410988053806
                ],
                [
                    0.0,
                    0.0,
                    105.80184171183244,
                    69.64957780887683
                ]
            ],
            [
                [
                    0.0,
                    0.0,
                    69.95454694454868,
                    169.86557543976232
                ],
                [
                    0.0,
                    0.0,
                    78.83277133818382,
                    135.0221197753384
                ]
            ]
        ],
        [
            [
                [
                    0.0,
                    0.0,
                    0.0,
                    141.14122419136388
                ],
                [
                    0.0,
                    0.0,
                    0.0,
                    122.10746172546101
                ]
            ],
            [
                [
                    0.0,
                    0.0,
                    0.0,
                    115.92552334596387
                ],
                [
                    0.0,
                    0.0,
                    0.0,
                    88.87362699681532
                ]
            ],
            [
                [
                    0.0,
                    0.0,
                    0.0,
                    124.96335673947414
                ],
                [
                    0.0,
                    0.0,
                    0.0,
                    99.07777019240939
                ]
            ],
            [
                [
                    0.0,
                    0.0,
                    0.0,
                    119.14769063366644
                ],
                [
                    0.0,
                    0.0,
                    0.0,
                    96.92486523724246
                ]
            ],
            [
                [
                    0.0,
                    0.0,
                    0.0,
                    131.74131289845417
                ],
                [
                    0.0,
                    0.0,
                    0.0,
                    98.39556510356947
                ]
            ],
            [
                [
                    0.0,
                    0.0,
                    0.0,
                    92.61604467392726
                ],
                [
                    0.0,
                    0.0,
                    0.0,
                    71.73882862387268
                ]
            ],
            [
                [
                    0.0,
                    0.0,
                    0.0,
                    126.3988045800905
                ],
                [
                    0.0,
                    0.0,
                    0.0,
                    173.25599921423185
                ]
            ],
            [
                [
                    0.0,
                    0.0,
                    0.0,
                    67.25293369777114
                ],
                [
                    0.0,
                    0.0,
                    0.0,
                    111.6751424621927
                ]
            ],
            [
                [
                    0.0,
                    0.0,
                    0.0,
                    119.16384177317364
                ],
                [
                    0.0,
                    0.0,
                    0.0,
                    107.35751366044441
                ]
            ],
            [
                [
                    0.0,
                    0.0,
                    0.0,
                    116.84649852853666
                ],
                [
                    0.0,
                    0.0,
                    0.0,
                    87.21286398951761
                ]
            ],
            [
                [
                    0.0,
                    0.0,
                    0.0,
                    124.8476304364122
                ],
                [
                    0.0,
                    0.0,
                    0.0,
                    97.7839371161502
                ]
            ],
            [
                [
                    0.0,
                    0.0,
                    0.0,
                    115.04332479152612
                ],
                [
                    0.0,
                    0.0,
                    0.0,
                    103.20814590679878
                ]
            ],
            [
                [
                    0.0,
                    0.0,
                    0.0,
                    128.52678907986922
                ],
                [
                    0.0,
                    0.0,
                    0.0,
                    89.9890355560596
                ]
            ],
            [
                [
                    0.0,
                    0.0,
                    0.0,
                    128.62760032469868
                ],
                [
                    0.0,
                    0.0,
                    0.0,
                    89.11375365793326
                ]
            ],
            [
                [
                    0.0,
                    0.0,
                    0.0,
                    125.7764407282848
                ],
                [
                    0.0,
                    0.0,
                    0.0,
                    87.58864508770438
                ]
            ],
            [
                [
                    0.0,
                    0.0,
                    0.0,
                    123.72556613915665
                ],
                [
                    0.0,
                    0.0,
                    0.0,
                    90.60794251091133
                ]
            ],
            [
                [
                    0.0,
                    0.0,
                    0.0,
                    117.94446602455744
                ],
                [
                    0.0,
                    0.0,
                    0.0,
                    92.98246364452581
                ]
            ],
            [
                [
                    0.0,
                    0.0,
                    0.0,
                    113.459913927488
                ],
                [
                    0.0,
                    0.0,
                    0.0,
                    97.3452595899528
                ]
            ],
            [
                [
                    0.0,
                    0.0,
                    0.0,
                    119.80869384127729
                ],
                [
                    0.0,
                    0.0,
                    0.0,
                    93.90140110581136
                ]
            ],
            [
                [
                    0.0,
                    0.0,
                    0.0,
                    127.92829700310232
                ],
                [
                    0.0,
                    0.0,
                    0.0,
                    110.94610517906848
                ]
            ]
        ]
    ],
    "mean_hatch_overstowage": [
        0.0,
        0.0,
        0.0
    ],
    "mean_ci": [
        1528.031123816967,
        1013.3158310889654,
        486.30921485938757
    ],
    "mean_demand": [
        12224.248990535736,
        8106.526648711723,
        3890.4737188751005
    ],
    "mean_revenue": [
        20354.53833191385,
        11416.06242605189,
        3934.01518633116
    ],
    "mean_cost": [
        0.0,
        0.0,
        0.0
    ],
    "mean_pd": [
        40.0,
        40.0,
        40.0
    ],
    "mean_mixing": [
        0.0,
        0.0,
        0.0
    ]
}