{
    "seed": 87,
    "ports": 4,
    "scenarios": 4,
    "obj": 36050.11511380391,
    "time": 1.8008129596710205,
    "gap": 0.0,
    "mean_load_per_port": [
        12508.490421772003,
        9888.252029566216,
        3934.6686854069662
    ],
    "mean_teu_load_per_port": [
        16936.127940654755,
        52736.58059100861,
        84758.70501825886
    ],
    "mean_load_per_location": [
        [
            [
                [
                    0.0,
                    0.0,
                    119.62110900878906,
                    321.47521209716797
                ],
                [
                    0.0,
                    0.0,
                    83.0,
                    334.0
                ]
            ],
            [
                [
                    0.0,
                    296.5382385253906,
                    0.0,
                    38.19575500488281
                ],
                [
                    0.0,
                    0.0,
                    0.0,
                    166.0
                ]
            ],
            [
                [
                    0.0,
                    0.0,
                    288.38340759277344,
                    0.0
                ],
                [
                    0.0,
                    0.0,
                    83.0,
                    0.0
                ]
            ],
            [
                [
                    0.0,
                    83.0,
                    167.0,
                    0.0
                ],
                [
                    0.0,
                    0.0,
                    0.0,
                    0.0
                ]
            ],
            [
                [
                    0.0,
                    167.0,
                    0.0,
                    83.0
                ],
                [
                    0.0,
                    167.0,
                    0.0,
                    166.0
                ]
            ],
            [
                [
                    0.0,
                    0.0,
                    0.0,
                    162.72673416137695
                ],
                [
                    0.0,
                    0.0,
                    0.0,
                    166.0
                ]
            ],
            [
                [
                    0.0,
                    84.78797507286072,
                    0.0,
                    96.126708984375
                ],
                [
                    0.0,
                    83.0,
                    0.0,
                    334.0
                ]
            ],
            [
                [
                    0.0,
                    0.0,
                    334.0,
                    0.0
                ],
                [
                    0.0,
                    0.0,
                    167.0,
                    83.0
                ]
            ],
            [
                [
                    0.0,
                    21.015952825546265,
                    331.3199295401573,
                    0.0
                ],
                [
                    0.0,
                    83.0,
                    334.0,
                    0.0
                ]
            ],
            [
                [
                    0.0,
                    166.0,
                    0.0,
                    169.8685783147812
                ],
                [
                    0.0,
                    124.35684204101562,
                    0.0,
                    334.0
                ]
            ],
            [
                [
                    0.0,
                    0.0,
                    158.9612274169922,
                    83.0
                ],
                [
                    0.0,
                    0.0,
                    239.52704620361328,
                    83.0
                ]
            ],
            [
                [
                    0.0,
                    245.1755142211914,
                    0.0,
                    0.0
                ],
                [
                    0.0,
                    460.0960693359375,
                    0.0,
                    0.0
                ]
            ],
            [
                [
                    0.0,
                    0.0,
                    437.5894021987915,
                    0.0
                ],
                [
                    0.0,
                    0.0,
                    420.70031696558,
                    0.0
                ]
            ],
            [
                [
                    0.0,
                    0.0,
                    0.0,
                    315.02245330810547
                ],
                [
                    0.0,
                    0.0,
                    0.0,
                    250.0
                ]
            ],
            [
                [
                    0.0,
                    74.75921630859375,
                    0.0,
                    167.0
                ],
                [
                    0.0,
                    0.0,
                    0.0,
                    277.087646484375
                ]
            ],
            [
                [
                    0.0,
                    0.0,
                    0.0,
                    333.0
                ],
                [
                    0.0,
                    0.0,
                    0.0,
                    334.0
                ]
            ],
            [
                [
                    0.0,
                    500.0,
                    0.0,
                    0.0
                ],
                [
                    0.0,
                    333.0,
                    0.0,
                    0.0
                ]
            ],
            [
                [
                    0.0,
                    83.0,
                    0.0,
                    167.0
                ],
                [
                    0.0,
                    166.0,
                    0.0,
                    230.5634914636612
                ]
            ],
            [
                [
                    0.0,
                    167.0,
                    0.0,
                    83.0
                ],
                [
                    0.0,
                    334.0,
                    0.0,
                    166.0
                ]
            ],
            [
                [
                    0.0,
                    95.59159469604492,
                    334.0,
                    0.0
                ],
                [
                    0.0,
                    166.0,
                    167.0,
                    0.0
                ]
            ]
        ],
        [
            [
                [
                    0.0,
                    0.0,
                    41.5,
                    259.2713451385498
                ],
                [
                    0.0,
                    0.0,
                    91.43455946069946,
                    212.16121541523938
                ]
            ],
            [
                [
                    0.0,
                    0.0,
                    88.08670353889465,
                    20.75
                ],
                [
                    0.0,
                    0.0,
                    186.2689151763916,
                    124.75
                ]
            ],
            [
                [
                    0.0,
                    0.0,
                    66.09282696247101,
                    286.9559555053711
                ],
                [
                    0.0,
                    0.0,
                    65.15963172912598,
                    151.70550626516342
                ]
            ],
            [
                [
                    0.0,
                    0.0,
                    157.83324646066706,
                    83.5
                ],
                [
                    0.0,
                    0.0,
                    136.6615982055664,
                    5.913469314575195
                ]
            ],
            [
                [
                    0.0,
                    0.0,
                    84.75408527255058,
                    129.51795908808708
                ],
                [
                    0.0,
                    0.0,
                    60.32481384277344,
                    124.75
                ]
            ],
            [
                [
                    0.0,
                    0.0,
                    37.9514274597168,
                    145.75
                ],
                [
                    0.0,
                    0.0,
                    12.401467323303223,
                    218.70744609832764
                ]
            ],
            [
                [
                    0.0,
                    0.0,
                    321.01648193597794,
                    77.11306823045015
                ],
                [
                    0.0,
                    0.0,
                    110.17957305908203,
                    83.0
                ]
            ],
            [
                [
                    0.0,
                    0.0,
                    122.22940754890442,
                    62.5
                ],
                [
                    0.0,
                    0.0,
                    60.35293102264404,
                    120.13397455215454
                ]
            ],
            [
                [
                    0.0,
                    0.0,
                    187.0,
                    125.25
                ],
                [
                    0.0,
                    0.0,
                    278.1037821173668,
                    126.76461791992188
                ]
            ],
            [
                [
                    0.0,
                    0.0,
                    131.20142572897416,
                    170.34908604621887
                ],
                [
                    0.0,
                    0.0,
                    90.66776125878096,
                    45.49905347824097
                ]
            ],
            [
                [
                    0.0,
                    0.0,
                    132.80405793339014,
                    157.2526683807373
                ],
                [
                    0.0,
                    0.0,
                    20.75,
                    138.93966245651245
                ]
            ],
            [
                [
                    0.0,
                    0.0,
                    26.206554412841797,
                    208.25
                ],
                [
                    0.0,
                    0.0,
                    91.1115550994873,
                    147.60891342163086
                ]
            ],
            [
                [
                    0.0,
                    0.0,
                    83.5,
                    134.8087629005313
                ],
                [
                    0.0,
                    0.0,
                    0.0,
                    167.29948806762695
                ]
            ],
            [
                [
                    0.0,
                    0.0,
                    128.8401539325714,
                    207.0041189789772
                ],
                [
                    0.0,
                    0.0,
                    130.1411736011505,
                    250.25
                ]
            ],
            [
                [
                    0.0,
                    0.0,
                    143.4367622062564,
                    21.0
                ],
                [
                    0.0,
                    0.0,
                    188.44473761320114,
                    89.27011489868164
                ]
            ],
            [
                [
                    0.0,
                    0.0,
                    179.41723543405533,
                    41.5
                ],
                [
                    0.0,
                    0.0,
                    198.58176889270544,
                    20.75
                ]
            ],
            [
                [
                    0.0,
                    0.0,
                    255.21895932406187,
                    77.21383666992188
                ],
                [
                    0.0,
                    0.0,
                    85.60053479671478,
                    17.60930061340332
                ]
            ],
            [
                [
                    0.0,
                    0.0,
                    132.11165672540665,
                    121.85930061340332
                ],
                [
                    0.0,
                    0.0,
                    145.75,
                    121.00409432500601
                ]
            ],
            [
                [
                    0.0,
                    0.0,
                    132.28897401690483,
                    124.5
                ],
                [
                    0.0,
                    0.0,
                    162.88872849941254,
                    82.95288062095642
                ]
            ],
            [
                [
                    0.0,
                    0.0,
                    153.71151556819677,
                    223.24525117874146
                ],
                [
                    0.0,
                    0.0,
                    121.04612731933594,
                    120.51980590820312
                ]
            ]
        ],
        [
            [
                [
                    0.0,
                    0.0,
                    0.0,
                    146.89242274133954
                ],
                [
                    0.0,
                    0.0,
                    0.0,
                    131.14183735847473
                ]
            ],
            [
                [
                    0.0,
                    0.0,
                    0.0,
                    73.32376557588577
                ],
                [
                    0.0,
                    0.0,
                    0.0,
                    64.28911072015762
                ]
            ],
            [
                [
                    0.0,
                    0.0,
                    0.0,
                    146.00744339849916
                ],
                [
                    0.0,
                    0.0,
                    0.0,
                    94.74207182671663
                ]
            ],
            [
                [
                    0.0,
                    0.0,
                    0.0,
                    58.60781644284725
                ],
                [
                    0.0,
                    0.0,
                    0.0,
                    91.3776882737875
                ]
            ],
            [
                [
                    0.0,
                    0.0,
                    0.0,
                    115.49475811305456
                ],
                [
                    0.0,
                    0.0,
                    0.0,
                    83.20988314625195
                ]
            ],
            [
                [
                    0.0,
                    0.0,
                    0.0,
                    60.904453724622726
                ],
                [
                    0.0,
                    0.0,
                    0.0,
                    53.39072201914391
                ]
            ],
            [
                [
                    0.0,
                    0.0,
                    0.0,
                    99.65904608252458
                ],
                [
                    0.0,
                    0.0,
                    0.0,
                    156.9399817287922
                ]
            ],
            [
                [
                    0.0,
                    0.0,
                    0.0,
                    85.51585359498858
                ],
                [
                    0.0,
                    0.0,
                    0.0,
                    77.30425032057693
                ]
            ],
            [
                [
                    0.0,
                    0.0,
                    0.0,
                    112.92261853814125
                ],
                [
                    0.0,
                    0.0,
                    0.0,
                    58.68008225654485
                ]
            ],
            [
                [
                    0.0,
                    0.0,
                    0.0,
                    74.38937693976331
                ],
                [
                    0.0,
                    0.0,
                    0.0,
                    79.93874037220625
                ]
            ],
            [
                [
                    0.0,
                    0.0,
                    0.0,
                    119.95870883390307
                ],
                [
                    0.0,
                    0.0,
                    0.0,
                    143.40260456489938
                ]
            ],
            [
                [
                    0.0,
                    0.0,
                    0.0,
                    71.02996091428213
                ],
                [
                    0.0,
                    0.0,
                    0.0,
                    97.99345839652462
                ]
            ],
            [
                [
                    0.0,
                    0.0,
                    0.0,
                    115.44952079281211
                ],
                [
                    0.0,
                    0.0,
                    0.0,
                    118.33898722566047
                ]
            ],
            [
                [
                    0.0,
                    0.0,
                    0.0,
                    167.53133435430937
                ],
                [
                    0.0,
                    0.0,
                    0.0,
                    61.858088731890746
                ]
            ],
            [
                [
                    0.0,
                    0.0,
                    0.0,
                    115.23167233052664
                ],
                [
                    0.0,
                    0.0,
                    0.0,
                    100.16074084761752
                ]
            ],
            [
                [
                    0.0,
                    0.0,
                    0.0,
                    128.7962513553095
                ],
                [
                    0.0,
                    0.0,
                    0.0,
                    42.605743631595544
                ]
            ],
            [
                [
                    0.0,
                    0.0,
                    0.0,
                    109.14844816095297
                ],
                [
                    0.0,
                    0.0,
                    0.0,
                    24.797602611902306
                ]
            ],
            [
                [
                    0.0,
                    0.0,
                    0.0,
                    107.58539514679927
                ],
                [
                    0.0,
                    0.0,
                    0.0,
                    78.0
                ]
            ],
            [
                [
                    0.0,
                    0.0,
                    0.0,
                    73.46251545410138
                ],
                [
                    0.0,
                    0.0,
                    0.0,
                    84.33271998154541
                ]
            ],
            [
                [
                    0.0,
                    0.0,
                    0.0,
                    194.68937513037585
                ],
                [
                    0.0,
                    0.0,
                    0.0,
                    115.56363376763903
                ]
            ]
        ]
    ],
    "mean_hatch_overstowage": [
        0.0,
        0.0,
        0.0
    ],
    "mean_ci": [
        1563.5613027215004,
        1137.8235825821757,
        432.335061366437
    ],
    "mean_demand": [
        12508.490421772003,
        9102.588660657406,
        3458.680490931496
    ],
    "mean_revenue": [
        21103.88852943114,
        12914.361200725087,
        3533.8410034421067
    ],
    "mean_cost": [
        0.0,
        0.0,
        0.0
    ],
    "mean_pd": [
        40.0,
        40.0,
        40.0
    ],
    "mean_mixing": [
        0.0,
        0.0,
        0.0
    ]
}